pbir_utils/__init__.py
pbir_utils/bookmark_utils.py
pbir_utils/cli.py
pbir_utils/command_utils.py
pbir_utils/common.py
pbir_utils/console_utils.py
pbir_utils/filter_clear.py
pbir_utils/filter_utils.py
pbir_utils/folder_standardizer.py
pbir_utils/metadata_extractor.py
pbir_utils/page_utils.py
pbir_utils/pbir_measure_utils.py
pbir_utils/pbir_processor.py
pbir_utils/pbir_report_sanitizer.py
pbir_utils/py.typed
pbir_utils/report_wireframe_visualizer.py
pbir_utils/rule_config.py
pbir_utils/rule_engine.py
pbir_utils/sanitize_config.py
pbir_utils/template_utils.py
pbir_utils/version_check.py
pbir_utils/visual_interactions_utils.py
pbir_utils/visual_utils.py
pbir_utils/api/__init__.py
pbir_utils/api/main.py
pbir_utils/api/models.py
pbir_utils/api/routes/__init__.py
pbir_utils/api/routes/browse.py
pbir_utils/api/routes/reports.py
pbir_utils/commands/__init__.py
pbir_utils/commands/batch_update.py
pbir_utils/commands/extract_metadata.py
pbir_utils/commands/filters.py
pbir_utils/commands/interactions.py
pbir_utils/commands/measures.py
pbir_utils/commands/pages.py
pbir_utils/commands/sanitize.py
pbir_utils/commands/ui.py
pbir_utils/commands/validate.py
pbir_utils/commands/visualize.py
pbir_utils/defaults/rules.yaml
pbir_utils/defaults/sanitize.yaml
pbir_utils/static/css/wireframe.css
pbir_utils/static/js/client.js
pbir_utils/static/js/wireframe.js
pbir_utils/templates/client.html.j2
pbir_utils/templates/wireframe.html.j2
pbir_utils/templates/wireframe_content.html.j2
pbir_utils-2.0.4.dist-info/licenses/LICENSE
pbir_utils-2.0.4.dist-info/METADATA
pbir_utils-2.0.4.dist-info/WHEEL
pbir_utils-2.0.4.dist-info/entry_points.txt
pbir_utils-2.0.4.dist-info/top_level.txt
pbir_utils-2.0.4.dist-info/RECORD
