Metadata-Version: 2.4
Name: pbir-utils
Version: 2.0.4
Summary: A tool for managing Power BI Enhanced Report Format (PBIR) projects
Author: Akhil Ashok
License: MIT License
Project-URL: Homepage, https://github.com/akhilannan/pbir-utils
Classifier: Intended Audience :: Developers
Classifier: Intended Audience :: Education
Classifier: Programming Language :: Python :: 3 :: Only
Classifier: License :: OSI Approved :: MIT License
Classifier: Operating System :: OS Independent
Requires-Python: >=3.10
License-File: LICENSE
Requires-Dist: jinja2
Requires-Dist: pyyaml
Requires-Dist: simpleeval
Provides-Extra: ui
Requires-Dist: fastapi; extra == "ui"
Requires-Dist: uvicorn[standard]; extra == "ui"
Requires-Dist: sse-starlette; extra == "ui"
Requires-Dist: python-multipart; extra == "ui"
Provides-Extra: dev
Requires-Dist: pytest; extra == "dev"
Requires-Dist: pytest-cov; extra == "dev"
Requires-Dist: httpx; extra == "dev"
Requires-Dist: ruff; extra == "dev"
Requires-Dist: black; extra == "dev"
Requires-Dist: bandit; extra == "dev"
Requires-Dist: build; extra == "dev"
Requires-Dist: twine; extra == "dev"
Provides-Extra: docs
Requires-Dist: mkdocs; extra == "docs"
Requires-Dist: mkdocs-material; extra == "docs"
Requires-Dist: requests; extra == "docs"
Dynamic: license-file
